nvflops/__init__.py
nvflops/_version.py
nvflops/agent/__init__.py
nvflops/agent/agent.py
nvflops/participant/__init__.py
nvflops/participant/client.py
nvflops/participant/participant.py
nvflops/participant/server.py
nvflops/tracker/__init__.py
nvflops/tracker/apis.py
nvflops/tracker/app.py
nvflops/tracker/config.py
nvflops/tracker/gunicorn.conf.py
nvflops/tracker/models.py
nvflops/utils/__init__.py
nvflops/utils/cert_utils.py
nvflops-0.0.1.dev2.dist-info/METADATA
nvflops-0.0.1.dev2.dist-info/WHEEL
nvflops-0.0.1.dev2.dist-info/top_level.txt
nvflops-0.0.1.dev2.dist-info/zip-safe
nvflops-0.0.1.dev2.dist-info/RECORD
