Metadata-Version: 2.1
Name: nvflops
Version: 0.0.1.dev2
Summary: The New Version of the Free-style machine-Learning Open Platform System
Home-page: https://github.com/IsaacYangSLA/nvflops
License: UNKNOWN
Platform: UNKNOWN
Classifier: Programming Language :: Python :: 3
Classifier: License :: Other/Proprietary License
Classifier: Operating System :: OS Independent
Requires-Python: >=3.7
Requires-Dist: boto3 (==1.21.24)
Requires-Dist: certifi (==2021.10.8)
Requires-Dist: flask (==2.0.3)
Requires-Dist: flask-sqlalchemy (==2.5.1)
Requires-Dist: minio (==7.1.5)
Requires-Dist: requests (==2.27.1)
Requires-Dist: python-dateutil (==2.8.2) ; python_version >= "2.7" and python_version not in "3.0, 3.1, 3.2, 3.3"
Requires-Dist: six (==1.16.0) ; python_version >= "2.7" and python_version not in "3.0, 3.1, 3.2, 3.3"
Requires-Dist: urllib3 (==1.26.9) ; python_version >= "2.7" and python_version not in "3.0, 3.1, 3.2, 3.3, 3.4" and python_version < "4"
Requires-Dist: sqlalchemy (==1.4.32) ; python_version >= "2.7" and python_version not in "3.0, 3.1, 3.2, 3.3, 3.4, 3.5"
Requires-Dist: charset-normalizer (==2.0.12) ; python_version >= "3"
Requires-Dist: idna (==3.3) ; python_version >= "3"
Requires-Dist: greenlet (==1.1.2) ; python_version >= "3" and platform_machine == "aarch64" or (platform_machine == "ppc64le" or (platform_machine == "x86_64" or (platform_machine == "amd64" or (platform_machine == "AMD64" or (platform_machine == "win32" or platform_machine == "WIN32")))))
Requires-Dist: botocore (==1.24.24) ; python_version >= "3.6"
Requires-Dist: click (==8.0.4) ; python_version >= "3.6"
Requires-Dist: jinja2 (==3.0.3) ; python_version >= "3.6"
Requires-Dist: s3transfer (==0.5.2) ; python_version >= "3.6"
Requires-Dist: werkzeug (==2.0.3) ; python_version >= "3.6"
Requires-Dist: itsdangerous (==2.1.1) ; python_version >= "3.7"
Requires-Dist: jmespath (==1.0.0) ; python_version >= "3.7"
Requires-Dist: markupsafe (==2.1.1) ; python_version >= "3.7"
